[
  {
     "nom":"player1",
     "score":"10000"
  },
  {
     "nom":"player2",
     "score":"20000"
  }
  {
     "nom":"player3",
     "score":"30000"
  }
  {
     "nom":"player4",
     "score":"40000"
  }
  {
     "nom":"player5",
     "score":"50000"
  }
  {
     "nom":"player6",
     "score":"60000"
  }
  {
     "nom":"player7",
     "score":"70000"
  }
  {
     "nom":"player8",
     "score":"80000"
  }
  {
     "nom":"player9",
     "score":"90000"
  }
  {
     "nom":"player10",
     "score":"100000"
  }

]
